MANIFEST.in
README.textile
README.textile~
setup.cfg
setup.py
pyJasper.egg-info/PKG-INFO
pyJasper.egg-info/SOURCES.txt
pyJasper.egg-info/dependency_links.txt
pyJasper.egg-info/not-zip-safe
pyJasper.egg-info/requires.txt
pyJasper.egg-info/top_level.txt
pyjasper/__init__.py
pyjasper/client.py
pyjasper/client_subreport.py
pyjasper/tests.py
pyjasper/backend/XmlJasperInterface.py
pyjasper/backend/__init__.py
pyjasper/backend/simplejson/__init__.py
pyjasper/backend/simplejson/decoder.py
pyjasper/backend/simplejson/encoder.py
pyjasper/backend/simplejson/ordered_dict.py
pyjasper/backend/simplejson/scanner.py
pyjasper/backend/simplejson/tool.py