Metadata-Version: 1.0
Name: pyJasper
Version: 0.41
Summary: toolkit to access JasperReports from Python
Home-page: https://github.com/hudora/pyJasper
Author: Maximillian Dornseif
Author-email: md@hudora.de
License: BSD
Platform: UNKNOWN
Classifier: Intended Audience :: Developers
Classifier: Programming Language :: Python
